json_matcher/__init__.py
json_matcher/json_matcher.py
json_matcher/match_environ.py
json_matcher-0.0.8.data/scripts/jrep
json_matcher-0.0.8.data/scripts/json_match
json_matcher-0.0.8.dist-info/LICENSE
json_matcher-0.0.8.dist-info/METADATA
json_matcher-0.0.8.dist-info/WHEEL
json_matcher-0.0.8.dist-info/top_level.txt
json_matcher-0.0.8.dist-info/RECORD
