Metadata-Version: 2.1
Name: json-matcher
Version: 0.0.8
Summary: Match json with lucece-like query
Home-page: https://github.com/hosung-yim/json_matcher
Author: Greg.YIM
Author-email: greg.yim@kakaocorp.com
License: UNKNOWN
Platform: any
Classifier: Development Status :: 4 - Beta
Classifier: Intended Audience :: Developers
Classifier: Operating System :: OS Independent
Classifier: Programming Language :: Python
Classifier: Programming Language :: Python :: 2
Classifier: Programming Language :: Python :: 3
Requires-Dist: pydash
Requires-Dist: pyparsing
Requires-Dist: six
